iaesdk/__init__.py
iaesdk/common.py
iaesdk/ibm_analytics_engine_api_v2.py
iaesdk/ibm_analytics_engine_api_v3.py
iaesdk/version.py
iaesdk-2.0.0.dist-info/LICENSE
iaesdk-2.0.0.dist-info/METADATA
iaesdk-2.0.0.dist-info/WHEEL
iaesdk-2.0.0.dist-info/top_level.txt
iaesdk-2.0.0.dist-info/zip-safe
iaesdk-2.0.0.dist-info/RECORD
