Metadata-Version: 2.1
Name: iaesdk
Version: 2.0.0
Summary: Python client library for IBM Cloud Analytics Engine Services
Home-page: https://github.com/IBM/ibm-iae-python-sdk
Author: IBM
Author-email: surya.penumatcha@ibm.com
License: Apache 2.0
Keywords: iaesdk
Classifier: Programming Language :: Python
Classifier: Programming Language :: Python :: 3
Classifier: Programming Language :: Python :: 3.7
Classifier: Programming Language :: Python :: 3.8
Classifier: Programming Language :: Python :: 3.9
Classifier: Programming Language :: Python :: 3.10
Classifier: Development Status :: 4 - Beta
Classifier: Intended Audience :: Developers
Classifier: License :: OSI Approved :: Apache Software License
Classifier: Operating System :: OS Independent
Classifier: Topic :: Software Development :: Libraries :: Python Modules
Classifier: Topic :: Software Development :: Libraries :: Application Frameworks
License-File: LICENSE
Requires-Dist: requests (<3.0.0,>=2.26.0)
Requires-Dist: urllib3 (<2.0.0,>=1.26.0)
Requires-Dist: python-dateutil (<3.0.0,>=2.5.3)
Requires-Dist: ibm-cloud-sdk-core (<4.0.0,>=3.16.0)
